setup.py
artifact/__init__.py
artifact.egg-info/PKG-INFO
artifact.egg-info/SOURCES.txt
artifact.egg-info/dependency_links.txt
artifact.egg-info/requires.txt
artifact.egg-info/top_level.txt
artifact.egg-info/zip-safe