Metadata-Version: 1.1
Name: artifact
Version: 0.0.1
Summary: WIP
Home-page: UNKNOWN
Author: Rossen Georgiev
Author-email: rossen@rgp.io
License: MIT
Keywords: valve steam artifact
Platform: UNKNOWN
Classifier: Development Status :: 4 - Beta
Classifier: Intended Audience :: Developers
Classifier: License :: OSI Approved :: MIT License
Classifier: Topic :: Software Development :: Libraries :: Python Modules
Classifier: Natural Language :: English
Classifier: Operating System :: OS Independent
Classifier: Programming Language :: Python :: 2.7
Classifier: Programming Language :: Python :: 3.4
Classifier: Programming Language :: Python :: 3.5
